[
  {
    "id": "student-1",
    "firstName": "Natalie",
    "lastName": "Mitchell",
    "email": "natalie.mitchell96@student.edu",
    "grade": 9,
    "school": "Lincoln High School",
    "beliefs": {
      "Political": "Moderate",
      "Economic": "Keynesian",
      "Environmental": "Skeptical",
      "Social": "Individualist",
      "Educational": "Constructivist"
    },
    "interests": [
      "Sports",
      "Science",
      "Healthcare",
      "History"
    ],
    "debateExperience": "Beginner",
    "communicationStyle": "Balanced",
    "joinDate": "2025-08-30T14:54:14.025Z",
    "stats": {
      "debatesParticipated": 5,
      "averageRating": "3.6",
      "topicsExplored": 8
    }
  },
  {
    "id": "student-2",
    "firstName": "Jackson",
    "lastName": "Nguyen",
    "email": "jackson.nguyen4@student.edu",
    "grade": 10,
    "school": "Jefferson Preparatory",
    "beliefs": {
      "Political": "Libertarian",
      "Economic": "Keynesian",
      "Environmental": "Moderate",
      "Social": "Individualist",
      "Educational": "Behaviorist"
    },
    "interests": [
      "International Relations",
      "Privacy Rights"
    ],
    "debateExperience": "Beginner",
    "communicationStyle": "Diplomatic",
    "joinDate": "2025-07-26T09:32:01.948Z",
    "stats": {
      "debatesParticipated": 16,
      "averageRating": "3.3",
      "topicsExplored": 9
    }
  },
  {
    "id": "student-3",
    "firstName": "Hudson",
    "lastName": "Gonzalez",
    "email": "hudson.gonzalez81@student.edu",
    "grade": 11,
    "school": "Lincoln High School",
    "beliefs": {
      "Political": "Libertarian",
      "Economic": "Keynesian",
      "Environmental": "Pragmatist",
      "Social": "Moderate",
      "Educational": "Behaviorist"
    },
    "interests": [
      "Literature",
      "Climate Change",
      "Science",
      "Education Reform",
      "Privacy Rights"
    ],
    "debateExperience": "Advanced",
    "communicationStyle": "Diplomatic",
    "joinDate": "2025-04-01T13:20:51.967Z",
    "stats": {
      "debatesParticipated": 9,
      "averageRating": "3.8",
      "topicsExplored": 10
    }
  },
  {
    "id": "student-4",
    "firstName": "Aiden",
    "lastName": "Ramirez",
    "email": "aiden.ramirez24@student.edu",
    "grade": 6,
    "school": "Jefferson Preparatory",
    "beliefs": {
      "Political": "Moderate",
      "Economic": "Austrian",
      "Environmental": "Skeptical",
      "Social": "Moderate",
      "Educational": "Progressive"
    },
    "interests": [
      "Mental Health",
      "Technology Ethics",
      "Climate Change",
      "Social Justice"
    ],
    "debateExperience": "Intermediate",
    "communicationStyle": "Balanced",
    "joinDate": "2025-06-09T21:42:42.504Z",
    "stats": {
      "debatesParticipated": 13,
      "averageRating": "3.3",
      "topicsExplored": 3
    }
  },
  {
    "id": "student-5",
    "firstName": "Sophia",
    "lastName": "Harris",
    "email": "sophia.harris81@student.edu",
    "grade": 10,
    "school": "Hamilton Institute",
    "beliefs": {
      "Political": "Conservative",
      "Economic": "Keynesian",
      "Environmental": "Skeptical",
      "Social": "Individualist",
      "Educational": "Eclectic"
    },
    "interests": [
      "Immigration",
      "Social Justice",
      "Artificial Intelligence",
      "Technology Ethics",
      "Philosophy"
    ],
    "debateExperience": "Intermediate",
    "communicationStyle": "Direct",
    "joinDate": "2025-05-18T09:13:13.496Z",
    "stats": {
      "debatesParticipated": 5,
      "averageRating": "4.3",
      "topicsExplored": 15
    }
  },
  {
    "id": "student-6",
    "firstName": "Logan",
    "lastName": "Hall",
    "email": "logan.hall29@student.edu",
    "grade": 9,
    "school": "Roosevelt Middle School",
    "beliefs": {
      "Political": "Conservative",
      "Economic": "Capitalist",
      "Environmental": "Conservationist",
      "Social": "Individualist",
      "Educational": "Progressive"
    },
    "interests": [
      "Arts & Culture",
      "Healthcare",
      "Economic Policy",
      "Technology Ethics",
      "Artificial Intelligence",
      "History"
    ],
    "debateExperience": "Intermediate",
    "communicationStyle": "Balanced",
    "joinDate": "2025-04-14T14:16:37.998Z",
    "stats": {
      "debatesParticipated": 14,
      "averageRating": "4.3",
      "topicsExplored": 11
    }
  },
  {
    "id": "student-7",
    "firstName": "Michael",
    "lastName": "Lopez",
    "email": "michael.lopez6@student.edu",
    "grade": 6,
    "school": "Jefferson Preparatory",
    "beliefs": {
      "Political": "Conservative",
      "Economic": "Capitalist",
      "Environmental": "Skeptical",
      "Social": "Moderate",
      "Educational": "Eclectic"
    },
    "interests": [
      "Climate Change",
      "Renewable Energy",
      "Literature",
      "Criminal Justice",
      "Economic Policy"
    ],
    "debateExperience": "Advanced",
    "communicationStyle": "Balanced",
    "joinDate": "2025-05-24T02:32:32.980Z",
    "stats": {
      "debatesParticipated": 4,
      "averageRating": "4.6",
      "topicsExplored": 13
    }
  },
  {
    "id": "student-8",
    "firstName": "Mila",
    "lastName": "Baker",
    "email": "mila.baker98@student.edu",
    "grade": 10,
    "school": "Washington Academy",
    "beliefs": {
      "Political": "Libertarian",
      "Economic": "Keynesian",
      "Environmental": "Skeptical",
      "Social": "Liberal",
      "Educational": "Progressive"
    },
    "interests": [
      "Philosophy",
      "Technology Ethics",
      "International Relations",
      "History",
      "Artificial Intelligence"
    ],
    "debateExperience": "Intermediate",
    "communicationStyle": "Direct",
    "joinDate": "2025-08-15T13:10:36.684Z",
    "stats": {
      "debatesParticipated": 1,
      "averageRating": "3.7",
      "topicsExplored": 7
    }
  },
  {
    "id": "student-9",
    "firstName": "Lily",
    "lastName": "Diaz",
    "email": "lily.diaz99@student.edu",
    "grade": 10,
    "school": "Jefferson Preparatory",
    "beliefs": {
      "Political": "Libertarian",
      "Economic": "Socialist",
      "Environmental": "Skeptical",
      "Social": "Moderate",
      "Educational": "Constructivist"
    },
    "interests": [
      "Economic Policy",
      "Healthcare",
      "Artificial Intelligence",
      "Climate Change",
      "Mental Health"
    ],
    "debateExperience": "Advanced",
    "communicationStyle": "Emotional",
    "joinDate": "2025-04-11T01:05:20.738Z",
    "stats": {
      "debatesParticipated": 1,
      "averageRating": "4.6",
      "topicsExplored": 15
    }
  },
  {
    "id": "student-10",
    "firstName": "Carter",
    "lastName": "Thomas",
    "email": "carter.thomas70@student.edu",
    "grade": 6,
    "school": "Hamilton Institute",
    "beliefs": {
      "Political": "Conservative",
      "Economic": "Capitalist",
      "Environmental": "Pragmatist",
      "Social": "Traditional",
      "Educational": "Eclectic"
    },
    "interests": [
      "Immigration",
      "Healthcare",
      "Education Reform",
      "Arts & Culture"
    ],
    "debateExperience": "Beginner",
    "communicationStyle": "Diplomatic",
    "joinDate": "2025-07-29T17:25:35.293Z",
    "stats": {
      "debatesParticipated": 10,
      "averageRating": "4.5",
      "topicsExplored": 5
    }
  },
  {
    "id": "student-11",
    "firstName": "Hannah",
    "lastName": "Walker",
    "email": "hannah.walker10@student.edu",
    "grade": 9,
    "school": "Lincoln High School",
    "beliefs": {
      "Political": "Moderate",
      "Economic": "Mixed Economy",
      "Environmental": "Moderate",
      "Social": "Moderate",
      "Educational": "Eclectic"
    },
    "interests": [
      "Science",
      "History",
      "Healthcare"
    ],
    "debateExperience": "Beginner",
    "communicationStyle": "Emotional",
    "joinDate": "2025-03-21T18:00:48.961Z",
    "stats": {
      "debatesParticipated": 18,
      "averageRating": "4.7",
      "topicsExplored": 9
    }
  },
  {
    "id": "student-12",
    "firstName": "Riley",
    "lastName": "Lewis",
    "email": "riley.lewis17@student.edu",
    "grade": 7,
    "school": "Adams Middle School",
    "beliefs": {
      "Political": "Moderate",
      "Economic": "Capitalist",
      "Environmental": "Pragmatist",
      "Social": "Traditional",
      "Educational": "Progressive"
    },
    "interests": [
      "Climate Change",
      "History",
      "Arts & Culture",
      "Criminal Justice",
      "Immigration",
      "Technology Ethics"
    ],
    "debateExperience": "Advanced",
    "communicationStyle": "Analytical",
    "joinDate": "2025-04-01T23:25:16.674Z",
    "stats": {
      "debatesParticipated": 7,
      "averageRating": "4.7",
      "topicsExplored": 11
    }
  },
  {
    "id": "student-13",
    "firstName": "Jaxon",
    "lastName": "Thomas",
    "email": "jaxon.thomas17@student.edu",
    "grade": 8,
    "school": "Franklin High School",
    "beliefs": {
      "Political": "Moderate",
      "Economic": "Mixed Economy",
      "Environmental": "Conservationist",
      "Social": "Individualist",
      "Educational": "Behaviorist"
    },
    "interests": [
      "Criminal Justice",
      "Education Reform",
      "Arts & Culture",
      "Sports",
      "Privacy Rights",
      "Technology Ethics"
    ],
    "debateExperience": "Beginner",
    "communicationStyle": "Diplomatic",
    "joinDate": "2025-08-20T14:21:45.641Z",
    "stats": {
      "debatesParticipated": 12,
      "averageRating": "3.4",
      "topicsExplored": 6
    }
  },
  {
    "id": "student-14",
    "firstName": "Taylor",
    "lastName": "Green",
    "email": "taylor.green53@student.edu",
    "grade": 11,
    "school": "Lincoln High School",
    "beliefs": {
      "Political": "Progressive",
      "Economic": "Keynesian",
      "Environmental": "Skeptical",
      "Social": "Moderate",
      "Educational": "Constructivist"
    },
    "interests": [
      "Arts & Culture",
      "Healthcare",
      "International Relations",
      "Renewable Energy"
    ],
    "debateExperience": "Advanced",
    "communicationStyle": "Emotional",
    "joinDate": "2025-05-31T19:26:57.804Z",
    "stats": {
      "debatesParticipated": 12,
      "averageRating": "4.6",
      "topicsExplored": 1
    }
  },
  {
    "id": "student-15",
    "firstName": "Olivia",
    "lastName": "Wright",
    "email": "olivia.wright70@student.edu",
    "grade": 12,
    "school": "Washington Academy",
    "beliefs": {
      "Political": "Conservative",
      "Economic": "Keynesian",
      "Environmental": "Conservationist",
      "Social": "Individualist",
      "Educational": "Traditional"
    },
    "interests": [
      "Healthcare",
      "Literature",
      "Artificial Intelligence"
    ],
    "debateExperience": "Advanced",
    "communicationStyle": "Emotional",
    "joinDate": "2025-03-15T07:56:01.575Z",
    "stats": {
      "debatesParticipated": 6,
      "averageRating": "4.7",
      "topicsExplored": 9
    }
  },
  {
    "id": "student-16",
    "firstName": "Aria",
    "lastName": "Smith",
    "email": "aria.smith37@student.edu",
    "grade": 12,
    "school": "Franklin High School",
    "beliefs": {
      "Political": "Independent",
      "Economic": "Capitalist",
      "Environmental": "Environmentalist",
      "Social": "Traditional",
      "Educational": "Behaviorist"
    },
    "interests": [
      "Education Reform",
      "Arts & Culture",
      "Technology Ethics",
      "Privacy Rights",
      "Renewable Energy",
      "Social Justice"
    ],
    "debateExperience": "Intermediate",
    "communicationStyle": "Direct",
    "joinDate": "2025-04-09T19:46:09.191Z",
    "stats": {
      "debatesParticipated": 16,
      "averageRating": "4.3",
      "topicsExplored": 5
    }
  },
  {
    "id": "student-17",
    "firstName": "Asher",
    "lastName": "Davis",
    "email": "asher.davis6@student.edu",
    "grade": 11,
    "school": "Washington Academy",
    "beliefs": {
      "Political": "Progressive",
      "Economic": "Austrian",
      "Environmental": "Environmentalist",
      "Social": "Moderate",
      "Educational": "Constructivist"
    },
    "interests": [
      "Immigration",
      "Sports"
    ],
    "debateExperience": "Intermediate",
    "communicationStyle": "Direct",
    "joinDate": "2025-04-11T22:19:46.579Z",
    "stats": {
      "debatesParticipated": 0,
      "averageRating": "4.1",
      "topicsExplored": 4
    }
  },
  {
    "id": "student-18",
    "firstName": "Mila",
    "lastName": "Jones",
    "email": "mila.jones60@student.edu",
    "grade": 11,
    "school": "Lincoln High School",
    "beliefs": {
      "Political": "Libertarian",
      "Economic": "Mixed Economy",
      "Environmental": "Environmentalist",
      "Social": "Communitarian",
      "Educational": "Progressive"
    },
    "interests": [
      "Economic Policy",
      "Literature",
      "Sports"
    ],
    "debateExperience": "Intermediate",
    "communicationStyle": "Balanced",
    "joinDate": "2025-04-26T02:42:46.965Z",
    "stats": {
      "debatesParticipated": 2,
      "averageRating": "4.6",
      "topicsExplored": 15
    }
  },
  {
    "id": "student-19",
    "firstName": "Henry",
    "lastName": "White",
    "email": "henry.white17@student.edu",
    "grade": 10,
    "school": "Adams Middle School",
    "beliefs": {
      "Political": "Progressive",
      "Economic": "Mixed Economy",
      "Environmental": "Conservationist",
      "Social": "Liberal",
      "Educational": "Constructivist"
    },
    "interests": [
      "Philosophy",
      "Technology Ethics",
      "Mental Health"
    ],
    "debateExperience": "Advanced",
    "communicationStyle": "Emotional",
    "joinDate": "2025-05-19T04:18:21.944Z",
    "stats": {
      "debatesParticipated": 14,
      "averageRating": "3.3",
      "topicsExplored": 5
    }
  },
  {
    "id": "student-20",
    "firstName": "Levi",
    "lastName": "Perez",
    "email": "levi.perez45@student.edu",
    "grade": 7,
    "school": "Hamilton Institute",
    "beliefs": {
      "Political": "Progressive",
      "Economic": "Socialist",
      "Environmental": "Skeptical",
      "Social": "Communitarian",
      "Educational": "Constructivist"
    },
    "interests": [
      "Renewable Energy",
      "Philosophy",
      "Literature",
      "Social Justice",
      "History"
    ],
    "debateExperience": "Intermediate",
    "communicationStyle": "Diplomatic",
    "joinDate": "2025-06-18T09:08:15.270Z",
    "stats": {
      "debatesParticipated": 6,
      "averageRating": "3.9",
      "topicsExplored": 6
    }
  },
  {
    "id": "student-21",
    "firstName": "Ellie",
    "lastName": "Gonzalez",
    "email": "ellie.gonzalez93@student.edu",
    "grade": 11,
    "school": "Lincoln High School",
    "beliefs": {
      "Political": "Conservative",
      "Economic": "Capitalist",
      "Environmental": "Pragmatist",
      "Social": "Moderate",
      "Educational": "Eclectic"
    },
    "interests": [
      "Healthcare",
      "Criminal Justice",
      "International Relations"
    ],
    "debateExperience": "Advanced",
    "communicationStyle": "Balanced",
    "joinDate": "2025-07-01T03:22:18.459Z",
    "stats": {
      "debatesParticipated": 18,
      "averageRating": "4.7",
      "topicsExplored": 2
    }
  },
  {
    "id": "student-22",
    "firstName": "Quinn",
    "lastName": "Torres",
    "email": "quinn.torres68@student.edu",
    "grade": 12,
    "school": "Adams Middle School",
    "beliefs": {
      "Political": "Independent",
      "Economic": "Capitalist",
      "Environmental": "Environmentalist",
      "Social": "Liberal",
      "Educational": "Traditional"
    },
    "interests": [
      "Science",
      "Arts & Culture",
      "Philosophy",
      "Immigration",
      "Criminal Justice"
    ],
    "debateExperience": "Beginner",
    "communicationStyle": "Balanced",
    "joinDate": "2025-06-16T03:17:04.945Z",
    "stats": {
      "debatesParticipated": 1,
      "averageRating": "4.0",
      "topicsExplored": 11
    }
  },
  {
    "id": "student-23",
    "firstName": "Harper",
    "lastName": "Taylor",
    "email": "harper.taylor3@student.edu",
    "grade": 7,
    "school": "Lincoln High School",
    "beliefs": {
      "Political": "Moderate",
      "Economic": "Mixed Economy",
      "Environmental": "Pragmatist",
      "Social": "Communitarian",
      "Educational": "Behaviorist"
    },
    "interests": [
      "Immigration",
      "Space Exploration",
      "Climate Change",
      "Healthcare"
    ],
    "debateExperience": "Intermediate",
    "communicationStyle": "Emotional",
    "joinDate": "2025-03-31T19:23:20.750Z",
    "stats": {
      "debatesParticipated": 3,
      "averageRating": "3.3",
      "topicsExplored": 5
    }
  },
  {
    "id": "student-24",
    "firstName": "Christopher",
    "lastName": "Lee",
    "email": "christopher.lee66@student.edu",
    "grade": 7,
    "school": "Jefferson Preparatory",
    "beliefs": {
      "Political": "Independent",
      "Economic": "Austrian",
      "Environmental": "Environmentalist",
      "Social": "Communitarian",
      "Educational": "Eclectic"
    },
    "interests": [
      "Immigration",
      "Education Reform",
      "Climate Change"
    ],
    "debateExperience": "Beginner",
    "communicationStyle": "Direct",
    "joinDate": "2025-09-06T02:37:37.493Z",
    "stats": {
      "debatesParticipated": 12,
      "averageRating": "4.6",
      "topicsExplored": 10
    }
  },
  {
    "id": "student-25",
    "firstName": "Alex",
    "lastName": "Wright",
    "email": "alex.wright5@student.edu",
    "grade": 7,
    "school": "Roosevelt Middle School",
    "beliefs": {
      "Political": "Independent",
      "Economic": "Keynesian",
      "Environmental": "Moderate",
      "Social": "Individualist",
      "Educational": "Eclectic"
    },
    "interests": [
      "Social Justice",
      "International Relations",
      "Artificial Intelligence",
      "Renewable Energy"
    ],
    "debateExperience": "Advanced",
    "communicationStyle": "Analytical",
    "joinDate": "2025-06-25T07:34:09.451Z",
    "stats": {
      "debatesParticipated": 18,
      "averageRating": "4.4",
      "topicsExplored": 12
    }
  },
  {
    "id": "student-26",
    "firstName": "Olivia",
    "lastName": "Rivera",
    "email": "olivia.rivera70@student.edu",
    "grade": 6,
    "school": "Washington Academy",
    "beliefs": {
      "Political": "Conservative",
      "Economic": "Mixed Economy",
      "Environmental": "Pragmatist",
      "Social": "Traditional",
      "Educational": "Progressive"
    },
    "interests": [
      "Arts & Culture",
      "History",
      "Healthcare",
      "Climate Change"
    ],
    "debateExperience": "Intermediate",
    "communicationStyle": "Diplomatic",
    "joinDate": "2025-06-03T21:59:38.111Z",
    "stats": {
      "debatesParticipated": 8,
      "averageRating": "4.7",
      "topicsExplored": 13
    }
  },
  {
    "id": "student-27",
    "firstName": "Jack",
    "lastName": "Lee",
    "email": "jack.lee42@student.edu",
    "grade": 9,
    "school": "Jefferson Preparatory",
    "beliefs": {
      "Political": "Conservative",
      "Economic": "Capitalist",
      "Environmental": "Conservationist",
      "Social": "Traditional",
      "Educational": "Progressive"
    },
    "interests": [
      "Artificial Intelligence",
      "Climate Change",
      "International Relations",
      "Education Reform",
      "Renewable Energy"
    ],
    "debateExperience": "Beginner",
    "communicationStyle": "Diplomatic",
    "joinDate": "2025-07-12T08:28:22.328Z",
    "stats": {
      "debatesParticipated": 18,
      "averageRating": "3.9",
      "topicsExplored": 3
    }
  },
  {
    "id": "student-28",
    "firstName": "Julian",
    "lastName": "Diaz",
    "email": "julian.diaz19@student.edu",
    "grade": 10,
    "school": "Jefferson Preparatory",
    "beliefs": {
      "Political": "Moderate",
      "Economic": "Mixed Economy",
      "Environmental": "Environmentalist",
      "Social": "Moderate",
      "Educational": "Progressive"
    },
    "interests": [
      "Science",
      "Immigration",
      "Healthcare",
      "Mental Health",
      "Economic Policy"
    ],
    "debateExperience": "Advanced",
    "communicationStyle": "Balanced",
    "joinDate": "2025-05-14T00:05:40.221Z",
    "stats": {
      "debatesParticipated": 18,
      "averageRating": "4.5",
      "topicsExplored": 13
    }
  },
  {
    "id": "student-29",
    "firstName": "Jaxon",
    "lastName": "Brown",
    "email": "jaxon.brown41@student.edu",
    "grade": 7,
    "school": "Hamilton Institute",
    "beliefs": {
      "Political": "Conservative",
      "Economic": "Capitalist",
      "Environmental": "Moderate",
      "Social": "Liberal",
      "Educational": "Behaviorist"
    },
    "interests": [
      "Space Exploration",
      "History",
      "Arts & Culture",
      "Climate Change"
    ],
    "debateExperience": "Beginner",
    "communicationStyle": "Diplomatic",
    "joinDate": "2025-08-01T10:55:14.380Z",
    "stats": {
      "debatesParticipated": 3,
      "averageRating": "3.3",
      "topicsExplored": 6
    }
  },
  {
    "id": "student-30",
    "firstName": "Mason",
    "lastName": "Sanchez",
    "email": "mason.sanchez73@student.edu",
    "grade": 10,
    "school": "Roosevelt Middle School",
    "beliefs": {
      "Political": "Progressive",
      "Economic": "Mixed Economy",
      "Environmental": "Environmentalist",
      "Social": "Liberal",
      "Educational": "Progressive"
    },
    "interests": [
      "Immigration",
      "Science",
      "Literature",
      "Education Reform",
      "Privacy Rights"
    ],
    "debateExperience": "Intermediate",
    "communicationStyle": "Analytical",
    "joinDate": "2025-03-21T02:23:19.469Z",
    "stats": {
      "debatesParticipated": 8,
      "averageRating": "4.9",
      "topicsExplored": 15
    }
  },
  {
    "id": "student-31",
    "firstName": "Casey",
    "lastName": "White",
    "email": "casey.white46@student.edu",
    "grade": 12,
    "school": "Adams Middle School",
    "beliefs": {
      "Political": "Progressive",
      "Economic": "Capitalist",
      "Environmental": "Pragmatist",
      "Social": "Traditional",
      "Educational": "Progressive"
    },
    "interests": [
      "Philosophy",
      "Space Exploration",
      "Climate Change",
      "Education Reform",
      "Arts & Culture",
      "Mental Health"
    ],
    "debateExperience": "Intermediate",
    "communicationStyle": "Balanced",
    "joinDate": "2025-07-25T13:47:04.326Z",
    "stats": {
      "debatesParticipated": 18,
      "averageRating": "4.7",
      "topicsExplored": 2
    }
  },
  {
    "id": "student-32",
    "firstName": "Ethan",
    "lastName": "Flores",
    "email": "ethan.flores99@student.edu",
    "grade": 8,
    "school": "Madison Charter School",
    "beliefs": {
      "Political": "Moderate",
      "Economic": "Capitalist",
      "Environmental": "Pragmatist",
      "Social": "Communitarian",
      "Educational": "Behaviorist"
    },
    "interests": [
      "Climate Change",
      "Privacy Rights",
      "International Relations",
      "Mental Health",
      "History"
    ],
    "debateExperience": "Intermediate",
    "communicationStyle": "Direct",
    "joinDate": "2025-07-29T21:04:30.268Z",
    "stats": {
      "debatesParticipated": 12,
      "averageRating": "3.8",
      "topicsExplored": 2
    }
  },
  {
    "id": "student-33",
    "firstName": "Aiden",
    "lastName": "Hall",
    "email": "aiden.hall61@student.edu",
    "grade": 9,
    "school": "Jefferson Preparatory",
    "beliefs": {
      "Political": "Independent",
      "Economic": "Austrian",
      "Environmental": "Skeptical",
      "Social": "Moderate",
      "Educational": "Behaviorist"
    },
    "interests": [
      "Economic Policy",
      "Education Reform",
      "International Relations"
    ],
    "debateExperience": "Beginner",
    "communicationStyle": "Direct",
    "joinDate": "2025-05-18T08:24:00.937Z",
    "stats": {
      "debatesParticipated": 14,
      "averageRating": "3.8",
      "topicsExplored": 3
    }
  },
  {
    "id": "student-34",
    "firstName": "Logan",
    "lastName": "King",
    "email": "logan.king35@student.edu",
    "grade": 10,
    "school": "Madison Charter School",
    "beliefs": {
      "Political": "Independent",
      "Economic": "Mixed Economy",
      "Environmental": "Skeptical",
      "Social": "Communitarian",
      "Educational": "Eclectic"
    },
    "interests": [
      "Philosophy",
      "Renewable Energy",
      "History",
      "Mental Health",
      "Healthcare"
    ],
    "debateExperience": "Intermediate",
    "communicationStyle": "Balanced",
    "joinDate": "2025-06-13T20:54:53.307Z",
    "stats": {
      "debatesParticipated": 5,
      "averageRating": "3.2",
      "topicsExplored": 10
    }
  },
  {
    "id": "student-35",
    "firstName": "Harper",
    "lastName": "Campbell",
    "email": "harper.campbell85@student.edu",
    "grade": 11,
    "school": "Franklin High School",
    "beliefs": {
      "Political": "Progressive",
      "Economic": "Keynesian",
      "Environmental": "Skeptical",
      "Social": "Traditional",
      "Educational": "Eclectic"
    },
    "interests": [
      "Space Exploration",
      "Criminal Justice",
      "Science"
    ],
    "debateExperience": "Advanced",
    "communicationStyle": "Balanced",
    "joinDate": "2025-05-12T02:50:26.612Z",
    "stats": {
      "debatesParticipated": 11,
      "averageRating": "4.2",
      "topicsExplored": 3
    }
  },
  {
    "id": "student-36",
    "firstName": "Jaxon",
    "lastName": "Walker",
    "email": "jaxon.walker91@student.edu",
    "grade": 9,
    "school": "Roosevelt Middle School",
    "beliefs": {
      "Political": "Libertarian",
      "Economic": "Socialist",
      "Environmental": "Environmentalist",
      "Social": "Moderate",
      "Educational": "Progressive"
    },
    "interests": [
      "History",
      "Arts & Culture",
      "Mental Health",
      "Climate Change",
      "Sports"
    ],
    "debateExperience": "Beginner",
    "communicationStyle": "Diplomatic",
    "joinDate": "2025-07-19T23:25:20.273Z",
    "stats": {
      "debatesParticipated": 8,
      "averageRating": "4.0",
      "topicsExplored": 15
    }
  },
  {
    "id": "student-37",
    "firstName": "Ellie",
    "lastName": "Thompson",
    "email": "ellie.thompson99@student.edu",
    "grade": 10,
    "school": "Lincoln High School",
    "beliefs": {
      "Political": "Moderate",
      "Economic": "Capitalist",
      "Environmental": "Skeptical",
      "Social": "Traditional",
      "Educational": "Traditional"
    },
    "interests": [
      "International Relations",
      "Science",
      "Mental Health",
      "Privacy Rights",
      "Renewable Energy",
      "Healthcare"
    ],
    "debateExperience": "Intermediate",
    "communicationStyle": "Direct",
    "joinDate": "2025-08-07T10:36:41.189Z",
    "stats": {
      "debatesParticipated": 19,
      "averageRating": "4.3",
      "topicsExplored": 9
    }
  },
  {
    "id": "student-38",
    "firstName": "Luke",
    "lastName": "Hill",
    "email": "luke.hill84@student.edu",
    "grade": 7,
    "school": "Lincoln High School",
    "beliefs": {
      "Political": "Libertarian",
      "Economic": "Keynesian",
      "Environmental": "Pragmatist",
      "Social": "Communitarian",
      "Educational": "Traditional"
    },
    "interests": [
      "Mental Health",
      "Literature",
      "Immigration",
      "Arts & Culture",
      "Philosophy"
    ],
    "debateExperience": "Beginner",
    "communicationStyle": "Direct",
    "joinDate": "2025-08-21T07:34:32.275Z",
    "stats": {
      "debatesParticipated": 14,
      "averageRating": "4.0",
      "topicsExplored": 7
    }
  },
  {
    "id": "student-39",
    "firstName": "Henry",
    "lastName": "Phillips",
    "email": "henry.phillips6@student.edu",
    "grade": 10,
    "school": "Hamilton Institute",
    "beliefs": {
      "Political": "Progressive",
      "Economic": "Socialist",
      "Environmental": "Conservationist",
      "Social": "Communitarian",
      "Educational": "Constructivist"
    },
    "interests": [
      "Immigration",
      "Philosophy",
      "Climate Change"
    ],
    "debateExperience": "Advanced",
    "communicationStyle": "Analytical",
    "joinDate": "2025-06-30T20:54:31.724Z",
    "stats": {
      "debatesParticipated": 17,
      "averageRating": "3.5",
      "topicsExplored": 2
    }
  },
  {
    "id": "student-40",
    "firstName": "Mila",
    "lastName": "Scott",
    "email": "mila.scott11@student.edu",
    "grade": 6,
    "school": "Madison Charter School",
    "beliefs": {
      "Political": "Moderate",
      "Economic": "Keynesian",
      "Environmental": "Moderate",
      "Social": "Liberal",
      "Educational": "Behaviorist"
    },
    "interests": [
      "Space Exploration",
      "Healthcare",
      "Economic Policy",
      "Renewable Energy"
    ],
    "debateExperience": "Intermediate",
    "communicationStyle": "Direct",
    "joinDate": "2025-05-21T14:59:44.981Z",
    "stats": {
      "debatesParticipated": 19,
      "averageRating": "4.6",
      "topicsExplored": 12
    }
  },
  {
    "id": "student-41",
    "firstName": "Annabelle",
    "lastName": "Miller",
    "email": "annabelle.miller33@student.edu",
    "grade": 7,
    "school": "Roosevelt Middle School",
    "beliefs": {
      "Political": "Libertarian",
      "Economic": "Keynesian",
      "Environmental": "Skeptical",
      "Social": "Moderate",
      "Educational": "Traditional"
    },
    "interests": [
      "Mental Health",
      "History"
    ],
    "debateExperience": "Intermediate",
    "communicationStyle": "Diplomatic",
    "joinDate": "2025-09-08T08:26:09.292Z",
    "stats": {
      "debatesParticipated": 10,
      "averageRating": "4.8",
      "topicsExplored": 2
    }
  },
  {
    "id": "student-42",
    "firstName": "Hudson",
    "lastName": "Jackson",
    "email": "hudson.jackson72@student.edu",
    "grade": 10,
    "school": "Hamilton Institute",
    "beliefs": {
      "Political": "Progressive",
      "Economic": "Keynesian",
      "Environmental": "Moderate",
      "Social": "Communitarian",
      "Educational": "Behaviorist"
    },
    "interests": [
      "Sports",
      "Arts & Culture",
      "Mental Health",
      "Social Justice"
    ],
    "debateExperience": "Beginner",
    "communicationStyle": "Direct",
    "joinDate": "2025-05-10T03:27:32.618Z",
    "stats": {
      "debatesParticipated": 14,
      "averageRating": "3.5",
      "topicsExplored": 8
    }
  },
  {
    "id": "student-43",
    "firstName": "Sophia",
    "lastName": "Jackson",
    "email": "sophia.jackson0@student.edu",
    "grade": 10,
    "school": "Washington Academy",
    "beliefs": {
      "Political": "Libertarian",
      "Economic": "Keynesian",
      "Environmental": "Moderate",
      "Social": "Moderate",
      "Educational": "Constructivist"
    },
    "interests": [
      "Criminal Justice",
      "Mental Health"
    ],
    "debateExperience": "Beginner",
    "communicationStyle": "Direct",
    "joinDate": "2025-06-12T04:35:03.028Z",
    "stats": {
      "debatesParticipated": 17,
      "averageRating": "4.0",
      "topicsExplored": 2
    }
  },
  {
    "id": "student-44",
    "firstName": "Jordan",
    "lastName": "Thomas",
    "email": "jordan.thomas17@student.edu",
    "grade": 10,
    "school": "Lincoln High School",
    "beliefs": {
      "Political": "Progressive",
      "Economic": "Socialist",
      "Environmental": "Skeptical",
      "Social": "Communitarian",
      "Educational": "Behaviorist"
    },
    "interests": [
      "Immigration",
      "Criminal Justice",
      "Economic Policy",
      "History"
    ],
    "debateExperience": "Beginner",
    "communicationStyle": "Direct",
    "joinDate": "2025-04-13T05:56:50.811Z",
    "stats": {
      "debatesParticipated": 1,
      "averageRating": "4.3",
      "topicsExplored": 3
    }
  },
  {
    "id": "student-45",
    "firstName": "Avery",
    "lastName": "Lewis",
    "email": "avery.lewis12@student.edu",
    "grade": 12,
    "school": "Jefferson Preparatory",
    "beliefs": {
      "Political": "Libertarian",
      "Economic": "Mixed Economy",
      "Environmental": "Conservationist",
      "Social": "Liberal",
      "Educational": "Progressive"
    },
    "interests": [
      "Space Exploration",
      "Artificial Intelligence",
      "Healthcare",
      "Science"
    ],
    "debateExperience": "Advanced",
    "communicationStyle": "Direct",
    "joinDate": "2025-04-30T13:20:57.876Z",
    "stats": {
      "debatesParticipated": 1,
      "averageRating": "3.6",
      "topicsExplored": 1
    }
  },
  {
    "id": "student-46",
    "firstName": "Taylor",
    "lastName": "Carter",
    "email": "taylor.carter30@student.edu",
    "grade": 10,
    "school": "Franklin High School",
    "beliefs": {
      "Political": "Libertarian",
      "Economic": "Austrian",
      "Environmental": "Moderate",
      "Social": "Liberal",
      "Educational": "Behaviorist"
    },
    "interests": [
      "History",
      "Privacy Rights",
      "Renewable Energy",
      "Mental Health",
      "International Relations"
    ],
    "debateExperience": "Beginner",
    "communicationStyle": "Diplomatic",
    "joinDate": "2025-04-20T06:47:50.818Z",
    "stats": {
      "debatesParticipated": 14,
      "averageRating": "4.7",
      "topicsExplored": 4
    }
  },
  {
    "id": "student-47",
    "firstName": "Quinn",
    "lastName": "Miller",
    "email": "quinn.miller11@student.edu",
    "grade": 7,
    "school": "Madison Charter School",
    "beliefs": {
      "Political": "Progressive",
      "Economic": "Austrian",
      "Environmental": "Conservationist",
      "Social": "Moderate",
      "Educational": "Eclectic"
    },
    "interests": [
      "Science",
      "Literature",
      "History"
    ],
    "debateExperience": "Advanced",
    "communicationStyle": "Emotional",
    "joinDate": "2025-07-01T05:16:45.594Z",
    "stats": {
      "debatesParticipated": 2,
      "averageRating": "3.1",
      "topicsExplored": 1
    }
  },
  {
    "id": "student-48",
    "firstName": "Sebastian",
    "lastName": "Turner",
    "email": "sebastian.turner60@student.edu",
    "grade": 7,
    "school": "Jefferson Preparatory",
    "beliefs": {
      "Political": "Libertarian",
      "Economic": "Socialist",
      "Environmental": "Pragmatist",
      "Social": "Liberal",
      "Educational": "Traditional"
    },
    "interests": [
      "Science",
      "Space Exploration",
      "International Relations",
      "Climate Change",
      "Mental Health"
    ],
    "debateExperience": "Advanced",
    "communicationStyle": "Direct",
    "joinDate": "2025-07-19T18:51:31.953Z",
    "stats": {
      "debatesParticipated": 9,
      "averageRating": "5.0",
      "topicsExplored": 11
    }
  },
  {
    "id": "student-49",
    "firstName": "Noah",
    "lastName": "Johnson",
    "email": "noah.johnson39@student.edu",
    "grade": 10,
    "school": "Hamilton Institute",
    "beliefs": {
      "Political": "Conservative",
      "Economic": "Keynesian",
      "Environmental": "Conservationist",
      "Social": "Moderate",
      "Educational": "Behaviorist"
    },
    "interests": [
      "Climate Change",
      "Literature",
      "Privacy Rights",
      "Technology Ethics"
    ],
    "debateExperience": "Intermediate",
    "communicationStyle": "Emotional",
    "joinDate": "2025-07-14T08:46:56.948Z",
    "stats": {
      "debatesParticipated": 8,
      "averageRating": "4.1",
      "topicsExplored": 13
    }
  },
  {
    "id": "student-50",
    "firstName": "Carter",
    "lastName": "Moore",
    "email": "carter.moore57@student.edu",
    "grade": 7,
    "school": "Franklin High School",
    "beliefs": {
      "Political": "Progressive",
      "Economic": "Capitalist",
      "Environmental": "Conservationist",
      "Social": "Traditional",
      "Educational": "Eclectic"
    },
    "interests": [
      "History",
      "Privacy Rights",
      "International Relations",
      "Criminal Justice"
    ],
    "debateExperience": "Advanced",
    "communicationStyle": "Direct",
    "joinDate": "2025-06-30T17:27:20.641Z",
    "stats": {
      "debatesParticipated": 8,
      "averageRating": "3.1",
      "topicsExplored": 15
    }
  },
  {
    "id": "student-51",
    "firstName": "Zoe",
    "lastName": "Johnson",
    "email": "zoe.johnson50@student.edu",
    "grade": 11,
    "school": "Roosevelt Middle School",
    "beliefs": {
      "Political": "Conservative",
      "Economic": "Austrian",
      "Environmental": "Pragmatist",
      "Social": "Liberal",
      "Educational": "Constructivist"
    },
    "interests": [
      "Technology Ethics",
      "Sports",
      "Privacy Rights",
      "Renewable Energy",
      "Philosophy"
    ],
    "debateExperience": "Beginner",
    "communicationStyle": "Emotional",
    "joinDate": "2025-08-21T08:24:23.294Z",
    "stats": {
      "debatesParticipated": 15,
      "averageRating": "4.1",
      "topicsExplored": 15
    }
  },
  {
    "id": "student-52",
    "firstName": "Zara",
    "lastName": "White",
    "email": "zara.white24@student.edu",
    "grade": 10,
    "school": "Lincoln High School",
    "beliefs": {
      "Political": "Conservative",
      "Economic": "Austrian",
      "Environmental": "Skeptical",
      "Social": "Communitarian",
      "Educational": "Constructivist"
    },
    "interests": [
      "Space Exploration",
      "Criminal Justice",
      "Social Justice",
      "Climate Change"
    ],
    "debateExperience": "Intermediate",
    "communicationStyle": "Direct",
    "joinDate": "2025-08-22T11:20:08.902Z",
    "stats": {
      "debatesParticipated": 9,
      "averageRating": "3.5",
      "topicsExplored": 2
    }
  },
  {
    "id": "student-53",
    "firstName": "Benjamin",
    "lastName": "Young",
    "email": "benjamin.young33@student.edu",
    "grade": 8,
    "school": "Madison Charter School",
    "beliefs": {
      "Political": "Conservative",
      "Economic": "Capitalist",
      "Environmental": "Moderate",
      "Social": "Communitarian",
      "Educational": "Behaviorist"
    },
    "interests": [
      "Renewable Energy",
      "Arts & Culture",
      "History",
      "Criminal Justice"
    ],
    "debateExperience": "Intermediate",
    "communicationStyle": "Balanced",
    "joinDate": "2025-04-29T14:20:48.785Z",
    "stats": {
      "debatesParticipated": 18,
      "averageRating": "3.0",
      "topicsExplored": 13
    }
  },
  {
    "id": "student-54",
    "firstName": "Mila",
    "lastName": "Hall",
    "email": "mila.hall81@student.edu",
    "grade": 10,
    "school": "Madison Charter School",
    "beliefs": {
      "Political": "Conservative",
      "Economic": "Mixed Economy",
      "Environmental": "Moderate",
      "Social": "Traditional",
      "Educational": "Traditional"
    },
    "interests": [
      "Climate Change",
      "Immigration",
      "Healthcare",
      "Privacy Rights"
    ],
    "debateExperience": "Intermediate",
    "communicationStyle": "Analytical",
    "joinDate": "2025-07-01T02:39:10.154Z",
    "stats": {
      "debatesParticipated": 6,
      "averageRating": "4.2",
      "topicsExplored": 5
    }
  },
  {
    "id": "student-55",
    "firstName": "Ellie",
    "lastName": "Allen",
    "email": "ellie.allen73@student.edu",
    "grade": 11,
    "school": "Madison Charter School",
    "beliefs": {
      "Political": "Progressive",
      "Economic": "Socialist",
      "Environmental": "Moderate",
      "Social": "Liberal",
      "Educational": "Constructivist"
    },
    "interests": [
      "Climate Change",
      "Space Exploration",
      "Technology Ethics",
      "Literature",
      "Science",
      "Philosophy"
    ],
    "debateExperience": "Beginner",
    "communicationStyle": "Analytical",
    "joinDate": "2025-08-18T14:29:50.654Z",
    "stats": {
      "debatesParticipated": 8,
      "averageRating": "3.3",
      "topicsExplored": 10
    }
  },
  {
    "id": "student-56",
    "firstName": "Theodore",
    "lastName": "Adams",
    "email": "theodore.adams37@student.edu",
    "grade": 11,
    "school": "Washington Academy",
    "beliefs": {
      "Political": "Conservative",
      "Economic": "Austrian",
      "Environmental": "Skeptical",
      "Social": "Communitarian",
      "Educational": "Constructivist"
    },
    "interests": [
      "Healthcare",
      "Technology Ethics",
      "International Relations",
      "Space Exploration",
      "Sports"
    ],
    "debateExperience": "Advanced",
    "communicationStyle": "Diplomatic",
    "joinDate": "2025-08-24T21:10:59.679Z",
    "stats": {
      "debatesParticipated": 0,
      "averageRating": "4.4",
      "topicsExplored": 9
    }
  },
  {
    "id": "student-57",
    "firstName": "Riley",
    "lastName": "Walker",
    "email": "riley.walker9@student.edu",
    "grade": 11,
    "school": "Washington Academy",
    "beliefs": {
      "Political": "Conservative",
      "Economic": "Mixed Economy",
      "Environmental": "Skeptical",
      "Social": "Communitarian",
      "Educational": "Behaviorist"
    },
    "interests": [
      "Literature",
      "Artificial Intelligence",
      "Economic Policy",
      "Space Exploration",
      "Sports",
      "Technology Ethics"
    ],
    "debateExperience": "Intermediate",
    "communicationStyle": "Balanced",
    "joinDate": "2025-08-24T10:06:55.075Z",
    "stats": {
      "debatesParticipated": 8,
      "averageRating": "3.1",
      "topicsExplored": 12
    }
  },
  {
    "id": "student-58",
    "firstName": "Victoria",
    "lastName": "Wilson",
    "email": "victoria.wilson92@student.edu",
    "grade": 9,
    "school": "Jefferson Preparatory",
    "beliefs": {
      "Political": "Conservative",
      "Economic": "Mixed Economy",
      "Environmental": "Pragmatist",
      "Social": "Individualist",
      "Educational": "Traditional"
    },
    "interests": [
      "Science",
      "Economic Policy",
      "Literature"
    ],
    "debateExperience": "Advanced",
    "communicationStyle": "Balanced",
    "joinDate": "2025-07-30T17:43:52.227Z",
    "stats": {
      "debatesParticipated": 9,
      "averageRating": "3.9",
      "topicsExplored": 6
    }
  },
  {
    "id": "student-59",
    "firstName": "Jordan",
    "lastName": "Walker",
    "email": "jordan.walker41@student.edu",
    "grade": 9,
    "school": "Adams Middle School",
    "beliefs": {
      "Political": "Independent",
      "Economic": "Socialist",
      "Environmental": "Environmentalist",
      "Social": "Moderate",
      "Educational": "Behaviorist"
    },
    "interests": [
      "Artificial Intelligence",
      "Healthcare",
      "Literature",
      "Arts & Culture",
      "Mental Health",
      "Climate Change"
    ],
    "debateExperience": "Beginner",
    "communicationStyle": "Emotional",
    "joinDate": "2025-07-30T05:06:46.417Z",
    "stats": {
      "debatesParticipated": 9,
      "averageRating": "3.0",
      "topicsExplored": 3
    }
  },
  {
    "id": "student-60",
    "firstName": "Morgan",
    "lastName": "Nguyen",
    "email": "morgan.nguyen83@student.edu",
    "grade": 11,
    "school": "Adams Middle School",
    "beliefs": {
      "Political": "Moderate",
      "Economic": "Austrian",
      "Environmental": "Moderate",
      "Social": "Individualist",
      "Educational": "Traditional"
    },
    "interests": [
      "Arts & Culture",
      "Space Exploration",
      "Literature",
      "Economic Policy"
    ],
    "debateExperience": "Intermediate",
    "communicationStyle": "Balanced",
    "joinDate": "2025-07-18T04:56:05.077Z",
    "stats": {
      "debatesParticipated": 13,
      "averageRating": "4.3",
      "topicsExplored": 15
    }
  },
  {
    "id": "student-61",
    "firstName": "Tessa",
    "lastName": "Roberts",
    "email": "tessa.roberts49@student.edu",
    "grade": 11,
    "school": "Madison Charter School",
    "beliefs": {
      "Political": "Conservative",
      "Economic": "Mixed Economy",
      "Environmental": "Pragmatist",
      "Social": "Traditional",
      "Educational": "Constructivist"
    },
    "interests": [
      "History",
      "Artificial Intelligence",
      "Sports"
    ],
    "debateExperience": "Advanced",
    "communicationStyle": "Emotional",
    "joinDate": "2025-03-17T22:50:31.556Z",
    "stats": {
      "debatesParticipated": 8,
      "averageRating": "4.9",
      "topicsExplored": 13
    }
  },
  {
    "id": "student-62",
    "firstName": "Hazel",
    "lastName": "Wilson",
    "email": "hazel.wilson97@student.edu",
    "grade": 12,
    "school": "Adams Middle School",
    "beliefs": {
      "Political": "Progressive",
      "Economic": "Keynesian",
      "Environmental": "Pragmatist",
      "Social": "Communitarian",
      "Educational": "Eclectic"
    },
    "interests": [
      "Literature",
      "Technology Ethics",
      "Space Exploration"
    ],
    "debateExperience": "Beginner",
    "communicationStyle": "Emotional",
    "joinDate": "2025-03-31T09:31:40.496Z",
    "stats": {
      "debatesParticipated": 7,
      "averageRating": "3.9",
      "topicsExplored": 15
    }
  },
  {
    "id": "student-63",
    "firstName": "Violet",
    "lastName": "Lewis",
    "email": "violet.lewis80@student.edu",
    "grade": 7,
    "school": "Madison Charter School",
    "beliefs": {
      "Political": "Moderate",
      "Economic": "Capitalist",
      "Environmental": "Environmentalist",
      "Social": "Liberal",
      "Educational": "Traditional"
    },
    "interests": [
      "Artificial Intelligence",
      "Arts & Culture",
      "Renewable Energy",
      "Healthcare",
      "Climate Change",
      "Economic Policy"
    ],
    "debateExperience": "Intermediate",
    "communicationStyle": "Analytical",
    "joinDate": "2025-06-19T12:40:55.255Z",
    "stats": {
      "debatesParticipated": 16,
      "averageRating": "4.9",
      "topicsExplored": 10
    }
  },
  {
    "id": "student-64",
    "firstName": "Keira",
    "lastName": "Evans",
    "email": "keira.evans88@student.edu",
    "grade": 11,
    "school": "Roosevelt Middle School",
    "beliefs": {
      "Political": "Progressive",
      "Economic": "Keynesian",
      "Environmental": "Pragmatist",
      "Social": "Liberal",
      "Educational": "Constructivist"
    },
    "interests": [
      "Space Exploration",
      "Mental Health",
      "International Relations"
    ],
    "debateExperience": "Advanced",
    "communicationStyle": "Direct",
    "joinDate": "2025-05-14T15:48:26.152Z",
    "stats": {
      "debatesParticipated": 4,
      "averageRating": "4.0",
      "topicsExplored": 13
    }
  },
  {
    "id": "student-65",
    "firstName": "John",
    "lastName": "Nelson",
    "email": "john.nelson97@student.edu",
    "grade": 10,
    "school": "Roosevelt Middle School",
    "beliefs": {
      "Political": "Progressive",
      "Economic": "Capitalist",
      "Environmental": "Conservationist",
      "Social": "Moderate",
      "Educational": "Constructivist"
    },
    "interests": [
      "International Relations",
      "Criminal Justice",
      "Sports",
      "Arts & Culture",
      "Climate Change",
      "Technology Ethics"
    ],
    "debateExperience": "Advanced",
    "communicationStyle": "Direct",
    "joinDate": "2025-05-26T06:12:44.310Z",
    "stats": {
      "debatesParticipated": 1,
      "averageRating": "4.3",
      "topicsExplored": 10
    }
  },
  {
    "id": "student-66",
    "firstName": "Mia",
    "lastName": "Jackson",
    "email": "mia.jackson65@student.edu",
    "grade": 12,
    "school": "Jefferson Preparatory",
    "beliefs": {
      "Political": "Libertarian",
      "Economic": "Socialist",
      "Environmental": "Skeptical",
      "Social": "Communitarian",
      "Educational": "Traditional"
    },
    "interests": [
      "Climate Change",
      "Education Reform",
      "Immigration",
      "Mental Health"
    ],
    "debateExperience": "Intermediate",
    "communicationStyle": "Balanced",
    "joinDate": "2025-08-03T00:02:35.942Z",
    "stats": {
      "debatesParticipated": 9,
      "averageRating": "4.5",
      "topicsExplored": 14
    }
  },
  {
    "id": "student-67",
    "firstName": "Nora",
    "lastName": "Smith",
    "email": "nora.smith44@student.edu",
    "grade": 12,
    "school": "Madison Charter School",
    "beliefs": {
      "Political": "Independent",
      "Economic": "Keynesian",
      "Environmental": "Skeptical",
      "Social": "Moderate",
      "Educational": "Progressive"
    },
    "interests": [
      "Renewable Energy",
      "Philosophy",
      "History"
    ],
    "debateExperience": "Beginner",
    "communicationStyle": "Direct",
    "joinDate": "2025-07-02T13:14:37.975Z",
    "stats": {
      "debatesParticipated": 1,
      "averageRating": "3.4",
      "topicsExplored": 8
    }
  },
  {
    "id": "student-68",
    "firstName": "Scarlett",
    "lastName": "King",
    "email": "scarlett.king77@student.edu",
    "grade": 6,
    "school": "Jefferson Preparatory",
    "beliefs": {
      "Political": "Independent",
      "Economic": "Capitalist",
      "Environmental": "Environmentalist",
      "Social": "Moderate",
      "Educational": "Traditional"
    },
    "interests": [
      "Philosophy",
      "Economic Policy",
      "Social Justice"
    ],
    "debateExperience": "Intermediate",
    "communicationStyle": "Analytical",
    "joinDate": "2025-03-24T07:17:06.001Z",
    "stats": {
      "debatesParticipated": 9,
      "averageRating": "3.9",
      "topicsExplored": 5
    }
  },
  {
    "id": "student-69",
    "firstName": "Alexander",
    "lastName": "Robinson",
    "email": "alexander.robinson86@student.edu",
    "grade": 7,
    "school": "Jefferson Preparatory",
    "beliefs": {
      "Political": "Conservative",
      "Economic": "Austrian",
      "Environmental": "Moderate",
      "Social": "Moderate",
      "Educational": "Traditional"
    },
    "interests": [
      "Philosophy",
      "Immigration",
      "Economic Policy"
    ],
    "debateExperience": "Beginner",
    "communicationStyle": "Balanced",
    "joinDate": "2025-05-13T05:13:45.042Z",
    "stats": {
      "debatesParticipated": 2,
      "averageRating": "4.7",
      "topicsExplored": 9
    }
  },
  {
    "id": "student-70",
    "firstName": "Casey",
    "lastName": "Williams",
    "email": "casey.williams66@student.edu",
    "grade": 12,
    "school": "Lincoln High School",
    "beliefs": {
      "Political": "Conservative",
      "Economic": "Capitalist",
      "Environmental": "Environmentalist",
      "Social": "Traditional",
      "Educational": "Traditional"
    },
    "interests": [
      "Technology Ethics",
      "International Relations",
      "Science",
      "Criminal Justice"
    ],
    "debateExperience": "Intermediate",
    "communicationStyle": "Diplomatic",
    "joinDate": "2025-04-27T13:48:17.483Z",
    "stats": {
      "debatesParticipated": 19,
      "averageRating": "3.0",
      "topicsExplored": 7
    }
  },
  {
    "id": "student-71",
    "firstName": "Asher",
    "lastName": "Walker",
    "email": "asher.walker56@student.edu",
    "grade": 10,
    "school": "Roosevelt Middle School",
    "beliefs": {
      "Political": "Conservative",
      "Economic": "Keynesian",
      "Environmental": "Environmentalist",
      "Social": "Individualist",
      "Educational": "Progressive"
    },
    "interests": [
      "International Relations",
      "Immigration",
      "History",
      "Economic Policy",
      "Sports"
    ],
    "debateExperience": "Beginner",
    "communicationStyle": "Emotional",
    "joinDate": "2025-05-10T06:33:32.414Z",
    "stats": {
      "debatesParticipated": 8,
      "averageRating": "4.2",
      "topicsExplored": 10
    }
  },
  {
    "id": "student-72",
    "firstName": "Ava",
    "lastName": "Davis",
    "email": "ava.davis95@student.edu",
    "grade": 7,
    "school": "Adams Middle School",
    "beliefs": {
      "Political": "Progressive",
      "Economic": "Mixed Economy",
      "Environmental": "Conservationist",
      "Social": "Liberal",
      "Educational": "Progressive"
    },
    "interests": [
      "Mental Health",
      "International Relations"
    ],
    "debateExperience": "Advanced",
    "communicationStyle": "Direct",
    "joinDate": "2025-04-03T14:08:06.072Z",
    "stats": {
      "debatesParticipated": 12,
      "averageRating": "4.5",
      "topicsExplored": 11
    }
  },
  {
    "id": "student-73",
    "firstName": "Chloe",
    "lastName": "Lewis",
    "email": "chloe.lewis43@student.edu",
    "grade": 11,
    "school": "Madison Charter School",
    "beliefs": {
      "Political": "Progressive",
      "Economic": "Capitalist",
      "Environmental": "Environmentalist",
      "Social": "Traditional",
      "Educational": "Constructivist"
    },
    "interests": [
      "Sports",
      "Literature",
      "Climate Change"
    ],
    "debateExperience": "Intermediate",
    "communicationStyle": "Analytical",
    "joinDate": "2025-08-15T19:07:18.464Z",
    "stats": {
      "debatesParticipated": 16,
      "averageRating": "3.8",
      "topicsExplored": 6
    }
  },
  {
    "id": "student-74",
    "firstName": "Thomas",
    "lastName": "Davis",
    "email": "thomas.davis17@student.edu",
    "grade": 12,
    "school": "Madison Charter School",
    "beliefs": {
      "Political": "Libertarian",
      "Economic": "Keynesian",
      "Environmental": "Conservationist",
      "Social": "Liberal",
      "Educational": "Traditional"
    },
    "interests": [
      "Healthcare",
      "Science",
      "Immigration"
    ],
    "debateExperience": "Advanced",
    "communicationStyle": "Analytical",
    "joinDate": "2025-07-25T14:12:27.959Z",
    "stats": {
      "debatesParticipated": 8,
      "averageRating": "3.8",
      "topicsExplored": 10
    }
  },
  {
    "id": "student-75",
    "firstName": "Christopher",
    "lastName": "Nguyen",
    "email": "christopher.nguyen41@student.edu",
    "grade": 9,
    "school": "Jefferson Preparatory",
    "beliefs": {
      "Political": "Conservative",
      "Economic": "Mixed Economy",
      "Environmental": "Skeptical",
      "Social": "Individualist",
      "Educational": "Progressive"
    },
    "interests": [
      "Literature",
      "International Relations",
      "Arts & Culture",
      "Science"
    ],
    "debateExperience": "Beginner",
    "communicationStyle": "Direct",
    "joinDate": "2025-08-09T07:22:18.978Z",
    "stats": {
      "debatesParticipated": 13,
      "averageRating": "3.9",
      "topicsExplored": 2
    }
  },
  {
    "id": "student-76",
    "firstName": "Daniel",
    "lastName": "Anderson",
    "email": "daniel.anderson28@student.edu",
    "grade": 6,
    "school": "Washington Academy",
    "beliefs": {
      "Political": "Conservative",
      "Economic": "Socialist",
      "Environmental": "Skeptical",
      "Social": "Traditional",
      "Educational": "Traditional"
    },
    "interests": [
      "Science",
      "Criminal Justice",
      "Education Reform",
      "Climate Change"
    ],
    "debateExperience": "Intermediate",
    "communicationStyle": "Diplomatic",
    "joinDate": "2025-05-17T04:07:38.252Z",
    "stats": {
      "debatesParticipated": 13,
      "averageRating": "3.9",
      "topicsExplored": 11
    }
  },
  {
    "id": "student-77",
    "firstName": "Riley",
    "lastName": "Parker",
    "email": "riley.parker19@student.edu",
    "grade": 10,
    "school": "Adams Middle School",
    "beliefs": {
      "Political": "Libertarian",
      "Economic": "Capitalist",
      "Environmental": "Moderate",
      "Social": "Liberal",
      "Educational": "Constructivist"
    },
    "interests": [
      "History",
      "Renewable Energy",
      "Artificial Intelligence",
      "Philosophy"
    ],
    "debateExperience": "Beginner",
    "communicationStyle": "Diplomatic",
    "joinDate": "2025-07-05T00:26:56.901Z",
    "stats": {
      "debatesParticipated": 11,
      "averageRating": "3.6",
      "topicsExplored": 10
    }
  },
  {
    "id": "student-78",
    "firstName": "Joseph",
    "lastName": "Roberts",
    "email": "joseph.roberts25@student.edu",
    "grade": 10,
    "school": "Madison Charter School",
    "beliefs": {
      "Political": "Independent",
      "Economic": "Austrian",
      "Environmental": "Environmentalist",
      "Social": "Individualist",
      "Educational": "Eclectic"
    },
    "interests": [
      "Climate Change",
      "Economic Policy",
      "History",
      "Privacy Rights",
      "Sports",
      "Technology Ethics"
    ],
    "debateExperience": "Intermediate",
    "communicationStyle": "Balanced",
    "joinDate": "2025-06-20T03:22:58.558Z",
    "stats": {
      "debatesParticipated": 11,
      "averageRating": "3.9",
      "topicsExplored": 15
    }
  },
  {
    "id": "student-79",
    "firstName": "Nora",
    "lastName": "Martinez",
    "email": "nora.martinez35@student.edu",
    "grade": 9,
    "school": "Jefferson Preparatory",
    "beliefs": {
      "Political": "Libertarian",
      "Economic": "Keynesian",
      "Environmental": "Moderate",
      "Social": "Traditional",
      "Educational": "Constructivist"
    },
    "interests": [
      "Economic Policy",
      "International Relations",
      "Privacy Rights",
      "Criminal Justice",
      "Social Justice"
    ],
    "debateExperience": "Advanced",
    "communicationStyle": "Emotional",
    "joinDate": "2025-07-24T13:50:30.290Z",
    "stats": {
      "debatesParticipated": 5,
      "averageRating": "3.5",
      "topicsExplored": 15
    }
  },
  {
    "id": "student-80",
    "firstName": "Tessa",
    "lastName": "King",
    "email": "tessa.king94@student.edu",
    "grade": 6,
    "school": "Washington Academy",
    "beliefs": {
      "Political": "Conservative",
      "Economic": "Austrian",
      "Environmental": "Moderate",
      "Social": "Moderate",
      "Educational": "Progressive"
    },
    "interests": [
      "Arts & Culture",
      "Space Exploration",
      "Privacy Rights"
    ],
    "debateExperience": "Advanced",
    "communicationStyle": "Balanced",
    "joinDate": "2025-05-10T00:14:32.855Z",
    "stats": {
      "debatesParticipated": 14,
      "averageRating": "3.1",
      "topicsExplored": 5
    }
  },
  {
    "id": "student-81",
    "firstName": "Ellie",
    "lastName": "Turner",
    "email": "ellie.turner62@student.edu",
    "grade": 6,
    "school": "Roosevelt Middle School",
    "beliefs": {
      "Political": "Moderate",
      "Economic": "Austrian",
      "Environmental": "Moderate",
      "Social": "Moderate",
      "Educational": "Progressive"
    },
    "interests": [
      "Mental Health",
      "Artificial Intelligence",
      "Economic Policy"
    ],
    "debateExperience": "Advanced",
    "communicationStyle": "Balanced",
    "joinDate": "2025-06-13T05:00:35.796Z",
    "stats": {
      "debatesParticipated": 15,
      "averageRating": "4.3",
      "topicsExplored": 7
    }
  },
  {
    "id": "student-82",
    "firstName": "Delilah",
    "lastName": "Ramirez",
    "email": "delilah.ramirez84@student.edu",
    "grade": 7,
    "school": "Jefferson Preparatory",
    "beliefs": {
      "Political": "Conservative",
      "Economic": "Capitalist",
      "Environmental": "Environmentalist",
      "Social": "Traditional",
      "Educational": "Eclectic"
    },
    "interests": [
      "Philosophy",
      "Arts & Culture",
      "Sports",
      "Education Reform"
    ],
    "debateExperience": "Beginner",
    "communicationStyle": "Balanced",
    "joinDate": "2025-06-25T20:14:37.811Z",
    "stats": {
      "debatesParticipated": 1,
      "averageRating": "4.2",
      "topicsExplored": 15
    }
  },
  {
    "id": "student-83",
    "firstName": "Charles",
    "lastName": "Perez",
    "email": "charles.perez32@student.edu",
    "grade": 11,
    "school": "Washington Academy",
    "beliefs": {
      "Political": "Independent",
      "Economic": "Capitalist",
      "Environmental": "Moderate",
      "Social": "Moderate",
      "Educational": "Progressive"
    },
    "interests": [
      "Technology Ethics",
      "International Relations",
      "Criminal Justice",
      "Immigration"
    ],
    "debateExperience": "Advanced",
    "communicationStyle": "Analytical",
    "joinDate": "2025-09-01T03:19:47.709Z",
    "stats": {
      "debatesParticipated": 12,
      "averageRating": "3.0",
      "topicsExplored": 5
    }
  },
  {
    "id": "student-84",
    "firstName": "Ezra",
    "lastName": "Garcia",
    "email": "ezra.garcia66@student.edu",
    "grade": 11,
    "school": "Madison Charter School",
    "beliefs": {
      "Political": "Progressive",
      "Economic": "Socialist",
      "Environmental": "Skeptical",
      "Social": "Communitarian",
      "Educational": "Progressive"
    },
    "interests": [
      "Criminal Justice",
      "International Relations",
      "Healthcare",
      "Social Justice",
      "Arts & Culture"
    ],
    "debateExperience": "Advanced",
    "communicationStyle": "Direct",
    "joinDate": "2025-06-14T05:01:43.202Z",
    "stats": {
      "debatesParticipated": 3,
      "averageRating": "4.8",
      "topicsExplored": 4
    }
  },
  {
    "id": "student-85",
    "firstName": "Riley",
    "lastName": "Lee",
    "email": "riley.lee25@student.edu",
    "grade": 6,
    "school": "Franklin High School",
    "beliefs": {
      "Political": "Libertarian",
      "Economic": "Mixed Economy",
      "Environmental": "Skeptical",
      "Social": "Individualist",
      "Educational": "Behaviorist"
    },
    "interests": [
      "Mental Health",
      "Immigration",
      "Arts & Culture"
    ],
    "debateExperience": "Advanced",
    "communicationStyle": "Diplomatic",
    "joinDate": "2025-07-19T21:52:19.070Z",
    "stats": {
      "debatesParticipated": 1,
      "averageRating": "4.9",
      "topicsExplored": 14
    }
  },
  {
    "id": "student-86",
    "firstName": "Aiden",
    "lastName": "Roberts",
    "email": "aiden.roberts38@student.edu",
    "grade": 6,
    "school": "Roosevelt Middle School",
    "beliefs": {
      "Political": "Moderate",
      "Economic": "Socialist",
      "Environmental": "Pragmatist",
      "Social": "Liberal",
      "Educational": "Progressive"
    },
    "interests": [
      "Education Reform",
      "Mental Health",
      "Renewable Energy",
      "Technology Ethics"
    ],
    "debateExperience": "Beginner",
    "communicationStyle": "Balanced",
    "joinDate": "2025-07-23T14:02:11.265Z",
    "stats": {
      "debatesParticipated": 9,
      "averageRating": "3.6",
      "topicsExplored": 9
    }
  },
  {
    "id": "student-87",
    "firstName": "Leah",
    "lastName": "Carter",
    "email": "leah.carter51@student.edu",
    "grade": 10,
    "school": "Roosevelt Middle School",
    "beliefs": {
      "Political": "Conservative",
      "Economic": "Austrian",
      "Environmental": "Pragmatist",
      "Social": "Individualist",
      "Educational": "Traditional"
    },
    "interests": [
      "Healthcare",
      "Sports",
      "Criminal Justice",
      "Space Exploration"
    ],
    "debateExperience": "Beginner",
    "communicationStyle": "Analytical",
    "joinDate": "2025-05-29T18:47:54.348Z",
    "stats": {
      "debatesParticipated": 17,
      "averageRating": "3.7",
      "topicsExplored": 6
    }
  },
  {
    "id": "student-88",
    "firstName": "Noah",
    "lastName": "Harris",
    "email": "noah.harris60@student.edu",
    "grade": 8,
    "school": "Washington Academy",
    "beliefs": {
      "Political": "Moderate",
      "Economic": "Austrian",
      "Environmental": "Pragmatist",
      "Social": "Traditional",
      "Educational": "Eclectic"
    },
    "interests": [
      "Climate Change",
      "Renewable Energy",
      "Arts & Culture",
      "Mental Health",
      "Science",
      "Space Exploration"
    ],
    "debateExperience": "Intermediate",
    "communicationStyle": "Diplomatic",
    "joinDate": "2025-05-26T09:46:55.933Z",
    "stats": {
      "debatesParticipated": 19,
      "averageRating": "3.7",
      "topicsExplored": 14
    }
  },
  {
    "id": "student-89",
    "firstName": "Mia",
    "lastName": "Allen",
    "email": "mia.allen47@student.edu",
    "grade": 8,
    "school": "Washington Academy",
    "beliefs": {
      "Political": "Libertarian",
      "Economic": "Socialist",
      "Environmental": "Environmentalist",
      "Social": "Moderate",
      "Educational": "Eclectic"
    },
    "interests": [
      "Space Exploration",
      "Literature"
    ],
    "debateExperience": "Advanced",
    "communicationStyle": "Emotional",
    "joinDate": "2025-04-24T03:49:12.287Z",
    "stats": {
      "debatesParticipated": 18,
      "averageRating": "4.5",
      "topicsExplored": 13
    }
  },
  {
    "id": "student-90",
    "firstName": "Sebastian",
    "lastName": "Young",
    "email": "sebastian.young71@student.edu",
    "grade": 8,
    "school": "Hamilton Institute",
    "beliefs": {
      "Political": "Libertarian",
      "Economic": "Austrian",
      "Environmental": "Skeptical",
      "Social": "Moderate",
      "Educational": "Constructivist"
    },
    "interests": [
      "International Relations",
      "Healthcare",
      "Renewable Energy"
    ],
    "debateExperience": "Beginner",
    "communicationStyle": "Analytical",
    "joinDate": "2025-07-02T07:46:33.847Z",
    "stats": {
      "debatesParticipated": 17,
      "averageRating": "3.1",
      "topicsExplored": 3
    }
  },
  {
    "id": "student-91",
    "firstName": "Avery",
    "lastName": "Roberts",
    "email": "avery.roberts93@student.edu",
    "grade": 11,
    "school": "Jefferson Preparatory",
    "beliefs": {
      "Political": "Conservative",
      "Economic": "Austrian",
      "Environmental": "Environmentalist",
      "Social": "Communitarian",
      "Educational": "Behaviorist"
    },
    "interests": [
      "Economic Policy",
      "Climate Change",
      "Education Reform",
      "Criminal Justice"
    ],
    "debateExperience": "Intermediate",
    "communicationStyle": "Balanced",
    "joinDate": "2025-03-26T12:48:53.452Z",
    "stats": {
      "debatesParticipated": 16,
      "averageRating": "4.2",
      "topicsExplored": 7
    }
  },
  {
    "id": "student-92",
    "firstName": "Grace",
    "lastName": "Gonzalez",
    "email": "grace.gonzalez54@student.edu",
    "grade": 6,
    "school": "Lincoln High School",
    "beliefs": {
      "Political": "Moderate",
      "Economic": "Mixed Economy",
      "Environmental": "Environmentalist",
      "Social": "Moderate",
      "Educational": "Behaviorist"
    },
    "interests": [
      "History",
      "Science",
      "Healthcare"
    ],
    "debateExperience": "Beginner",
    "communicationStyle": "Balanced",
    "joinDate": "2025-09-06T22:29:32.540Z",
    "stats": {
      "debatesParticipated": 10,
      "averageRating": "4.6",
      "topicsExplored": 1
    }
  },
  {
    "id": "student-93",
    "firstName": "Henry",
    "lastName": "Turner",
    "email": "henry.turner97@student.edu",
    "grade": 6,
    "school": "Jefferson Preparatory",
    "beliefs": {
      "Political": "Conservative",
      "Economic": "Austrian",
      "Environmental": "Conservationist",
      "Social": "Communitarian",
      "Educational": "Eclectic"
    },
    "interests": [
      "Science",
      "Technology Ethics",
      "Education Reform",
      "Philosophy"
    ],
    "debateExperience": "Advanced",
    "communicationStyle": "Diplomatic",
    "joinDate": "2025-09-04T10:39:15.291Z",
    "stats": {
      "debatesParticipated": 0,
      "averageRating": "4.2",
      "topicsExplored": 5
    }
  },
  {
    "id": "student-94",
    "firstName": "Christopher",
    "lastName": "Lee",
    "email": "christopher.lee83@student.edu",
    "grade": 10,
    "school": "Roosevelt Middle School",
    "beliefs": {
      "Political": "Conservative",
      "Economic": "Socialist",
      "Environmental": "Skeptical",
      "Social": "Liberal",
      "Educational": "Constructivist"
    },
    "interests": [
      "Privacy Rights",
      "Criminal Justice",
      "Immigration",
      "Technology Ethics",
      "Sports"
    ],
    "debateExperience": "Advanced",
    "communicationStyle": "Diplomatic",
    "joinDate": "2025-08-24T23:22:03.603Z",
    "stats": {
      "debatesParticipated": 9,
      "averageRating": "4.1",
      "topicsExplored": 6
    }
  },
  {
    "id": "student-95",
    "firstName": "Hannah",
    "lastName": "Davis",
    "email": "hannah.davis34@student.edu",
    "grade": 7,
    "school": "Lincoln High School",
    "beliefs": {
      "Political": "Moderate",
      "Economic": "Capitalist",
      "Environmental": "Moderate",
      "Social": "Traditional",
      "Educational": "Eclectic"
    },
    "interests": [
      "Artificial Intelligence",
      "Literature",
      "Technology Ethics",
      "Climate Change",
      "Social Justice"
    ],
    "debateExperience": "Intermediate",
    "communicationStyle": "Balanced",
    "joinDate": "2025-08-16T17:20:14.465Z",
    "stats": {
      "debatesParticipated": 0,
      "averageRating": "3.5",
      "topicsExplored": 2
    }
  },
  {
    "id": "student-96",
    "firstName": "Amelia",
    "lastName": "Carter",
    "email": "amelia.carter99@student.edu",
    "grade": 10,
    "school": "Jefferson Preparatory",
    "beliefs": {
      "Political": "Progressive",
      "Economic": "Socialist",
      "Environmental": "Skeptical",
      "Social": "Individualist",
      "Educational": "Traditional"
    },
    "interests": [
      "Criminal Justice",
      "Social Justice",
      "Education Reform",
      "Philosophy",
      "Healthcare",
      "International Relations"
    ],
    "debateExperience": "Advanced",
    "communicationStyle": "Emotional",
    "joinDate": "2025-05-22T20:36:15.015Z",
    "stats": {
      "debatesParticipated": 8,
      "averageRating": "3.2",
      "topicsExplored": 10
    }
  },
  {
    "id": "student-97",
    "firstName": "Daniel",
    "lastName": "Garcia",
    "email": "daniel.garcia45@student.edu",
    "grade": 8,
    "school": "Lincoln High School",
    "beliefs": {
      "Political": "Independent",
      "Economic": "Mixed Economy",
      "Environmental": "Conservationist",
      "Social": "Communitarian",
      "Educational": "Constructivist"
    },
    "interests": [
      "International Relations",
      "Renewable Energy",
      "Social Justice",
      "Arts & Culture",
      "Privacy Rights"
    ],
    "debateExperience": "Intermediate",
    "communicationStyle": "Direct",
    "joinDate": "2025-06-09T16:21:49.011Z",
    "stats": {
      "debatesParticipated": 1,
      "averageRating": "3.6",
      "topicsExplored": 2
    }
  },
  {
    "id": "student-98",
    "firstName": "Maya",
    "lastName": "Miller",
    "email": "maya.miller55@student.edu",
    "grade": 10,
    "school": "Franklin High School",
    "beliefs": {
      "Political": "Moderate",
      "Economic": "Mixed Economy",
      "Environmental": "Moderate",
      "Social": "Liberal",
      "Educational": "Traditional"
    },
    "interests": [
      "Literature",
      "Mental Health",
      "Climate Change"
    ],
    "debateExperience": "Intermediate",
    "communicationStyle": "Analytical",
    "joinDate": "2025-04-16T19:29:23.386Z",
    "stats": {
      "debatesParticipated": 1,
      "averageRating": "4.7",
      "topicsExplored": 3
    }
  },
  {
    "id": "student-99",
    "firstName": "Elizabeth",
    "lastName": "Torres",
    "email": "elizabeth.torres32@student.edu",
    "grade": 11,
    "school": "Lincoln High School",
    "beliefs": {
      "Political": "Conservative",
      "Economic": "Capitalist",
      "Environmental": "Pragmatist",
      "Social": "Traditional",
      "Educational": "Traditional"
    },
    "interests": [
      "Economic Policy",
      "Literature",
      "Artificial Intelligence",
      "Science",
      "Climate Change"
    ],
    "debateExperience": "Advanced",
    "communicationStyle": "Analytical",
    "joinDate": "2025-06-20T02:07:29.085Z",
    "stats": {
      "debatesParticipated": 10,
      "averageRating": "4.3",
      "topicsExplored": 1
    }
  },
  {
    "id": "student-100",
    "firstName": "Ethan",
    "lastName": "Allen",
    "email": "ethan.allen38@student.edu",
    "grade": 10,
    "school": "Jefferson Preparatory",
    "beliefs": {
      "Political": "Progressive",
      "Economic": "Socialist",
      "Environmental": "Conservationist",
      "Social": "Moderate",
      "Educational": "Behaviorist"
    },
    "interests": [
      "Philosophy",
      "Arts & Culture",
      "Privacy Rights",
      "Education Reform"
    ],
    "debateExperience": "Intermediate",
    "communicationStyle": "Diplomatic",
    "joinDate": "2025-09-09T19:13:48.805Z",
    "stats": {
      "debatesParticipated": 4,
      "averageRating": "4.5",
      "topicsExplored": 9
    }
  },
  {
    "id": "student-101",
    "firstName": "Chloe",
    "lastName": "White",
    "email": "chloe.white28@student.edu",
    "grade": 7,
    "school": "Hamilton Institute",
    "beliefs": {
      "Political": "Progressive",
      "Economic": "Mixed Economy",
      "Environmental": "Environmentalist",
      "Social": "Moderate",
      "Educational": "Traditional"
    },
    "interests": [
      "Renewable Energy",
      "Privacy Rights",
      "Mental Health"
    ],
    "debateExperience": "Advanced",
    "communicationStyle": "Emotional",
    "joinDate": "2025-04-11T16:31:56.499Z",
    "stats": {
      "debatesParticipated": 4,
      "averageRating": "3.1",
      "topicsExplored": 14
    }
  },
  {
    "id": "student-102",
    "firstName": "Julian",
    "lastName": "Lewis",
    "email": "julian.lewis52@student.edu",
    "grade": 6,
    "school": "Washington Academy",
    "beliefs": {
      "Political": "Libertarian",
      "Economic": "Socialist",
      "Environmental": "Skeptical",
      "Social": "Individualist",
      "Educational": "Progressive"
    },
    "interests": [
      "Mental Health",
      "Literature",
      "Sports",
      "Renewable Energy",
      "Healthcare"
    ],
    "debateExperience": "Beginner",
    "communicationStyle": "Diplomatic",
    "joinDate": "2025-05-10T20:33:23.195Z",
    "stats": {
      "debatesParticipated": 11,
      "averageRating": "4.8",
      "topicsExplored": 4
    }
  },
  {
    "id": "student-103",
    "firstName": "Aiden",
    "lastName": "Williams",
    "email": "aiden.williams20@student.edu",
    "grade": 7,
    "school": "Roosevelt Middle School",
    "beliefs": {
      "Political": "Progressive",
      "Economic": "Socialist",
      "Environmental": "Moderate",
      "Social": "Liberal",
      "Educational": "Eclectic"
    },
    "interests": [
      "Arts & Culture",
      "Technology Ethics",
      "Literature"
    ],
    "debateExperience": "Advanced",
    "communicationStyle": "Balanced",
    "joinDate": "2025-05-17T16:07:34.313Z",
    "stats": {
      "debatesParticipated": 11,
      "averageRating": "4.6",
      "topicsExplored": 2
    }
  },
  {
    "id": "student-104",
    "firstName": "Benjamin",
    "lastName": "Gomez",
    "email": "benjamin.gomez78@student.edu",
    "grade": 7,
    "school": "Washington Academy",
    "beliefs": {
      "Political": "Independent",
      "Economic": "Capitalist",
      "Environmental": "Skeptical",
      "Social": "Liberal",
      "Educational": "Constructivist"
    },
    "interests": [
      "Economic Policy",
      "Arts & Culture",
      "Education Reform",
      "Mental Health"
    ],
    "debateExperience": "Advanced",
    "communicationStyle": "Analytical",
    "joinDate": "2025-07-13T12:48:34.419Z",
    "stats": {
      "debatesParticipated": 12,
      "averageRating": "4.7",
      "topicsExplored": 11
    }
  },
  {
    "id": "student-105",
    "firstName": "Luke",
    "lastName": "Evans",
    "email": "luke.evans34@student.edu",
    "grade": 11,
    "school": "Washington Academy",
    "beliefs": {
      "Political": "Progressive",
      "Economic": "Socialist",
      "Environmental": "Skeptical",
      "Social": "Traditional",
      "Educational": "Constructivist"
    },
    "interests": [
      "Science",
      "Renewable Energy",
      "Healthcare",
      "Sports",
      "Philosophy"
    ],
    "debateExperience": "Advanced",
    "communicationStyle": "Diplomatic",
    "joinDate": "2025-07-03T02:19:47.541Z",
    "stats": {
      "debatesParticipated": 19,
      "averageRating": "3.9",
      "topicsExplored": 14
    }
  },
  {
    "id": "student-106",
    "firstName": "James",
    "lastName": "Gonzalez",
    "email": "james.gonzalez10@student.edu",
    "grade": 11,
    "school": "Lincoln High School",
    "beliefs": {
      "Political": "Independent",
      "Economic": "Austrian",
      "Environmental": "Environmentalist",
      "Social": "Liberal",
      "Educational": "Traditional"
    },
    "interests": [
      "Economic Policy",
      "Social Justice",
      "Arts & Culture",
      "Technology Ethics",
      "Immigration"
    ],
    "debateExperience": "Intermediate",
    "communicationStyle": "Diplomatic",
    "joinDate": "2025-07-03T05:04:51.851Z",
    "stats": {
      "debatesParticipated": 9,
      "averageRating": "3.0",
      "topicsExplored": 5
    }
  },
  {
    "id": "student-107",
    "firstName": "Quinn",
    "lastName": "Johnson",
    "email": "quinn.johnson83@student.edu",
    "grade": 8,
    "school": "Madison Charter School",
    "beliefs": {
      "Political": "Progressive",
      "Economic": "Austrian",
      "Environmental": "Moderate",
      "Social": "Communitarian",
      "Educational": "Traditional"
    },
    "interests": [
      "Philosophy",
      "Education Reform",
      "Arts & Culture",
      "Economic Policy"
    ],
    "debateExperience": "Beginner",
    "communicationStyle": "Analytical",
    "joinDate": "2025-07-16T00:27:42.282Z",
    "stats": {
      "debatesParticipated": 10,
      "averageRating": "4.6",
      "topicsExplored": 1
    }
  },
  {
    "id": "student-108",
    "firstName": "Jackson",
    "lastName": "Carter",
    "email": "jackson.carter41@student.edu",
    "grade": 11,
    "school": "Roosevelt Middle School",
    "beliefs": {
      "Political": "Conservative",
      "Economic": "Keynesian",
      "Environmental": "Pragmatist",
      "Social": "Traditional",
      "Educational": "Traditional"
    },
    "interests": [
      "Immigration",
      "Mental Health",
      "Renewable Energy",
      "Climate Change",
      "Arts & Culture"
    ],
    "debateExperience": "Advanced",
    "communicationStyle": "Balanced",
    "joinDate": "2025-03-26T04:19:24.375Z",
    "stats": {
      "debatesParticipated": 4,
      "averageRating": "3.1",
      "topicsExplored": 15
    }
  },
  {
    "id": "student-109",
    "firstName": "Benjamin",
    "lastName": "Gomez",
    "email": "benjamin.gomez95@student.edu",
    "grade": 12,
    "school": "Hamilton Institute",
    "beliefs": {
      "Political": "Independent",
      "Economic": "Socialist",
      "Environmental": "Moderate",
      "Social": "Moderate",
      "Educational": "Traditional"
    },
    "interests": [
      "Healthcare",
      "Literature",
      "Arts & Culture"
    ],
    "debateExperience": "Beginner",
    "communicationStyle": "Emotional",
    "joinDate": "2025-07-07T12:22:52.043Z",
    "stats": {
      "debatesParticipated": 2,
      "averageRating": "4.1",
      "topicsExplored": 8
    }
  },
  {
    "id": "student-110",
    "firstName": "James",
    "lastName": "Martin",
    "email": "james.martin33@student.edu",
    "grade": 11,
    "school": "Washington Academy",
    "beliefs": {
      "Political": "Conservative",
      "Economic": "Capitalist",
      "Environmental": "Conservationist",
      "Social": "Moderate",
      "Educational": "Traditional"
    },
    "interests": [
      "Mental Health",
      "History",
      "Healthcare"
    ],
    "debateExperience": "Intermediate",
    "communicationStyle": "Emotional",
    "joinDate": "2025-09-03T07:56:59.421Z",
    "stats": {
      "debatesParticipated": 14,
      "averageRating": "4.6",
      "topicsExplored": 4
    }
  },
  {
    "id": "student-111",
    "firstName": "Isabella",
    "lastName": "Allen",
    "email": "isabella.allen67@student.edu",
    "grade": 8,
    "school": "Franklin High School",
    "beliefs": {
      "Political": "Conservative",
      "Economic": "Socialist",
      "Environmental": "Pragmatist",
      "Social": "Communitarian",
      "Educational": "Traditional"
    },
    "interests": [
      "Mental Health",
      "International Relations",
      "Renewable Energy"
    ],
    "debateExperience": "Intermediate",
    "communicationStyle": "Balanced",
    "joinDate": "2025-05-07T19:21:14.667Z",
    "stats": {
      "debatesParticipated": 6,
      "averageRating": "4.5",
      "topicsExplored": 2
    }
  },
  {
    "id": "student-112",
    "firstName": "Benjamin",
    "lastName": "Carter",
    "email": "benjamin.carter41@student.edu",
    "grade": 6,
    "school": "Franklin High School",
    "beliefs": {
      "Political": "Libertarian",
      "Economic": "Socialist",
      "Environmental": "Environmentalist",
      "Social": "Liberal",
      "Educational": "Behaviorist"
    },
    "interests": [
      "Arts & Culture",
      "Science",
      "Artificial Intelligence",
      "Immigration"
    ],
    "debateExperience": "Advanced",
    "communicationStyle": "Emotional",
    "joinDate": "2025-08-24T04:01:36.755Z",
    "stats": {
      "debatesParticipated": 17,
      "averageRating": "4.7",
      "topicsExplored": 11
    }
  },
  {
    "id": "student-113",
    "firstName": "William",
    "lastName": "White",
    "email": "william.white1@student.edu",
    "grade": 7,
    "school": "Jefferson Preparatory",
    "beliefs": {
      "Political": "Independent",
      "Economic": "Austrian",
      "Environmental": "Conservationist",
      "Social": "Traditional",
      "Educational": "Behaviorist"
    },
    "interests": [
      "Sports",
      "Science",
      "Renewable Energy"
    ],
    "debateExperience": "Advanced",
    "communicationStyle": "Balanced",
    "joinDate": "2025-03-16T12:59:13.819Z",
    "stats": {
      "debatesParticipated": 0,
      "averageRating": "4.7",
      "topicsExplored": 7
    }
  },
  {
    "id": "student-114",
    "firstName": "Sofia",
    "lastName": "Jones",
    "email": "sofia.jones91@student.edu",
    "grade": 6,
    "school": "Lincoln High School",
    "beliefs": {
      "Political": "Libertarian",
      "Economic": "Mixed Economy",
      "Environmental": "Moderate",
      "Social": "Individualist",
      "Educational": "Constructivist"
    },
    "interests": [
      "Education Reform",
      "Philosophy",
      "Healthcare"
    ],
    "debateExperience": "Intermediate",
    "communicationStyle": "Emotional",
    "joinDate": "2025-07-05T14:39:21.723Z",
    "stats": {
      "debatesParticipated": 15,
      "averageRating": "4.4",
      "topicsExplored": 13
    }
  },
  {
    "id": "student-115",
    "firstName": "Jayden",
    "lastName": "Baker",
    "email": "jayden.baker95@student.edu",
    "grade": 11,
    "school": "Hamilton Institute",
    "beliefs": {
      "Political": "Conservative",
      "Economic": "Keynesian",
      "Environmental": "Pragmatist",
      "Social": "Individualist",
      "Educational": "Behaviorist"
    },
    "interests": [
      "History",
      "Sports",
      "Healthcare",
      "Criminal Justice",
      "Science",
      "Artificial Intelligence"
    ],
    "debateExperience": "Advanced",
    "communicationStyle": "Balanced",
    "joinDate": "2025-05-13T01:41:22.681Z",
    "stats": {
      "debatesParticipated": 9,
      "averageRating": "3.5",
      "topicsExplored": 8
    }
  },
  {
    "id": "student-116",
    "firstName": "Carter",
    "lastName": "Gomez",
    "email": "carter.gomez40@student.edu",
    "grade": 7,
    "school": "Washington Academy",
    "beliefs": {
      "Political": "Independent",
      "Economic": "Capitalist",
      "Environmental": "Pragmatist",
      "Social": "Liberal",
      "Educational": "Progressive"
    },
    "interests": [
      "Social Justice",
      "Sports",
      "Privacy Rights",
      "Artificial Intelligence"
    ],
    "debateExperience": "Intermediate",
    "communicationStyle": "Analytical",
    "joinDate": "2025-05-12T00:49:31.091Z",
    "stats": {
      "debatesParticipated": 12,
      "averageRating": "4.9",
      "topicsExplored": 1
    }
  },
  {
    "id": "student-117",
    "firstName": "Chloe",
    "lastName": "Scott",
    "email": "chloe.scott63@student.edu",
    "grade": 7,
    "school": "Franklin High School",
    "beliefs": {
      "Political": "Progressive",
      "Economic": "Socialist",
      "Environmental": "Pragmatist",
      "Social": "Traditional",
      "Educational": "Eclectic"
    },
    "interests": [
      "Healthcare",
      "Literature",
      "Arts & Culture",
      "Privacy Rights",
      "Mental Health",
      "Education Reform"
    ],
    "debateExperience": "Beginner",
    "communicationStyle": "Balanced",
    "joinDate": "2025-06-01T01:03:39.825Z",
    "stats": {
      "debatesParticipated": 12,
      "averageRating": "3.9",
      "topicsExplored": 13
    }
  },
  {
    "id": "student-118",
    "firstName": "Theodore",
    "lastName": "Taylor",
    "email": "theodore.taylor6@student.edu",
    "grade": 12,
    "school": "Lincoln High School",
    "beliefs": {
      "Political": "Progressive",
      "Economic": "Socialist",
      "Environmental": "Moderate",
      "Social": "Communitarian",
      "Educational": "Behaviorist"
    },
    "interests": [
      "Science",
      "Artificial Intelligence",
      "Sports",
      "Immigration"
    ],
    "debateExperience": "Intermediate",
    "communicationStyle": "Diplomatic",
    "joinDate": "2025-04-20T15:50:28.965Z",
    "stats": {
      "debatesParticipated": 14,
      "averageRating": "4.0",
      "topicsExplored": 12
    }
  },
  {
    "id": "student-119",
    "firstName": "Asher",
    "lastName": "Carter",
    "email": "asher.carter55@student.edu",
    "grade": 10,
    "school": "Madison Charter School",
    "beliefs": {
      "Political": "Libertarian",
      "Economic": "Austrian",
      "Environmental": "Pragmatist",
      "Social": "Liberal",
      "Educational": "Eclectic"
    },
    "interests": [
      "Criminal Justice",
      "Literature",
      "History",
      "International Relations",
      "Social Justice"
    ],
    "debateExperience": "Intermediate",
    "communicationStyle": "Analytical",
    "joinDate": "2025-03-23T22:40:31.948Z",
    "stats": {
      "debatesParticipated": 3,
      "averageRating": "4.6",
      "topicsExplored": 12
    }
  },
  {
    "id": "student-120",
    "firstName": "Hazel",
    "lastName": "Adams",
    "email": "hazel.adams64@student.edu",
    "grade": 9,
    "school": "Roosevelt Middle School",
    "beliefs": {
      "Political": "Progressive",
      "Economic": "Keynesian",
      "Environmental": "Moderate",
      "Social": "Moderate",
      "Educational": "Eclectic"
    },
    "interests": [
      "Artificial Intelligence",
      "Immigration"
    ],
    "debateExperience": "Intermediate",
    "communicationStyle": "Balanced",
    "joinDate": "2025-06-17T09:03:44.205Z",
    "stats": {
      "debatesParticipated": 3,
      "averageRating": "4.0",
      "topicsExplored": 8
    }
  }
]